panedr/__init__.py
panedr/panedr.py
panedr/tests/__init__.py
panedr/tests/test_edr.py
panedr-0.8.0.dist-info/AUTHORS
panedr-0.8.0.dist-info/LICENSE.txt
panedr-0.8.0.dist-info/METADATA
panedr-0.8.0.dist-info/WHEEL
panedr-0.8.0.dist-info/top_level.txt
panedr-0.8.0.dist-info/RECORD
