Metadata-Version: 2.1
Name: panedr
Version: 0.8.0
Summary: Read Gromacs EDR files and expose them as pandas Dataframes
Author-email: Jonathan Barnoud <jonathan@barnoud.net>
Maintainer-email: The MDAnalysis developers <mdanalysis@numfocus.org>
License: LGPLv2+
Project-URL: Homepage, https://github.com/MDAnalysis/panedr
Classifier: Development Status :: 4 - Beta
Classifier: Intended Audience :: Developers
Classifier: Topic :: Scientific/Engineering :: Bio-Informatics
Classifier: Topic :: Scientific/Engineering :: Chemistry
Classifier: Topic :: Scientific/Engineering :: Physics
Classifier: License :: OSI Approved :: GNU Lesser General Public License v2 or later (LGPLv2+)
Classifier: Programming Language :: Python :: 3.9
Classifier: Programming Language :: Python :: 3.10
Classifier: Programming Language :: Python :: 3.11
Classifier: Programming Language :: Python :: 3.12
Classifier: Operating System :: OS Independent
Requires-Python: >=3.9
License-File: LICENSE.txt
License-File: AUTHORS
Requires-Dist: pyedr
Requires-Dist: pandas
Provides-Extra: test
Requires-Dist: pytest; extra == "test"
Requires-Dist: pytest-xdist; extra == "test"
